odoo10_addon_hr_holidays_jours_ouvrables-10.0.1.0.0.99.dev13-py3.8-nspkg.pth
odoo/addons/hr_holidays_jours_ouvrables/README.rst
odoo/addons/hr_holidays_jours_ouvrables/__init__.py
odoo/addons/hr_holidays_jours_ouvrables/__manifest__.py
odoo/addons/hr_holidays_jours_ouvrables/i18n/am.po
odoo/addons/hr_holidays_jours_ouvrables/i18n/ca.po
odoo/addons/hr_holidays_jours_ouvrables/i18n/de.po
odoo/addons/hr_holidays_jours_ouvrables/i18n/el_GR.po
odoo/addons/hr_holidays_jours_ouvrables/i18n/es.po
odoo/addons/hr_holidays_jours_ouvrables/i18n/es_ES.po
odoo/addons/hr_holidays_jours_ouvrables/i18n/fi.po
odoo/addons/hr_holidays_jours_ouvrables/i18n/fr.po
odoo/addons/hr_holidays_jours_ouvrables/i18n/gl.po
odoo/addons/hr_holidays_jours_ouvrables/i18n/hr_holidays_jours_ouvrables.pot
odoo/addons/hr_holidays_jours_ouvrables/i18n/it.po
odoo/addons/hr_holidays_jours_ouvrables/i18n/nb_NO.po
odoo/addons/hr_holidays_jours_ouvrables/i18n/pt.po
odoo/addons/hr_holidays_jours_ouvrables/i18n/pt_BR.po
odoo/addons/hr_holidays_jours_ouvrables/i18n/pt_PT.po
odoo/addons/hr_holidays_jours_ouvrables/i18n/sl.po
odoo/addons/hr_holidays_jours_ouvrables/i18n/tr.po
odoo/addons/hr_holidays_jours_ouvrables/models/__init__.py
odoo/addons/hr_holidays_jours_ouvrables/models/hr_holidays.py
odoo/addons/hr_holidays_jours_ouvrables/models/hr_holidays_employee_saturday.py
odoo/addons/hr_holidays_jours_ouvrables/models/hr_holidays_status.py
odoo/addons/hr_holidays_jours_ouvrables/models/res_company.py
odoo/addons/hr_holidays_jours_ouvrables/security/ir.model.access.csv
odoo/addons/hr_holidays_jours_ouvrables/static/description/icon.png
odoo/addons/hr_holidays_jours_ouvrables/tests/__init__.py
odoo/addons/hr_holidays_jours_ouvrables/tests/common.py
odoo/addons/hr_holidays_jours_ouvrables/tests/test_holidays_compute.py
odoo/addons/hr_holidays_jours_ouvrables/tests/test_saturdays.py
odoo/addons/hr_holidays_jours_ouvrables/views/hr_holidays_status_views.xml
odoo10_addon_hr_holidays_jours_ouvrables-10.0.1.0.0.99.dev13.dist-info/METADATA
odoo10_addon_hr_holidays_jours_ouvrables-10.0.1.0.0.99.dev13.dist-info/WHEEL
odoo10_addon_hr_holidays_jours_ouvrables-10.0.1.0.0.99.dev13.dist-info/namespace_packages.txt
odoo10_addon_hr_holidays_jours_ouvrables-10.0.1.0.0.99.dev13.dist-info/top_level.txt
odoo10_addon_hr_holidays_jours_ouvrables-10.0.1.0.0.99.dev13.dist-info/RECORD
